{
	"_version": "1.1.0",
	"resources": [
		{
			"name": ".theming",
			"size": 90,
			"theme": "sap_fiori_3"
		},
		{
			"name": "ContextMenu.less",
			"size": 2661,
			"designtime": true,
			"theme": "sap_fiori_3"
		},
		{
			"name": "Dialogs.less",
			"size": 1998,
			"designtime": true,
			"theme": "sap_fiori_3"
		},
		{
			"name": "FieldRepository.less",
			"size": 1724,
			"designtime": true,
			"theme": "sap_fiori_3"
		},
		{
			"name": "Overlay.less",
			"size": 531,
			"designtime": true,
			"theme": "sap_fiori_3"
		},
		{
			"name": "Toolbar.adaptation.less",
			"size": 332,
			"designtime": true,
			"theme": "sap_fiori_3"
		},
		{
			"name": "Toolbar.base.less",
			"size": 733,
			"designtime": true,
			"theme": "sap_fiori_3"
		},
		{
			"name": "Toolbar.personalization.less",
			"size": 290,
			"designtime": true,
			"theme": "sap_fiori_3"
		},
		{
			"name": "Toolbar.standalone.less",
			"size": 262,
			"designtime": true,
			"theme": "sap_fiori_3"
		},
		{
			"name": "css_variables.css",
			"size": 7725,
			"theme": "sap_fiori_3"
		},
		{
			"name": "css_variables.less",
			"size": 94759,
			"designtime": true,
			"theme": "sap_fiori_3"
		},
		{
			"name": "css_variables.source.less",
			"size": 94391,
			"designtime": true,
			"theme": "sap_fiori_3"
		},
		{
			"name": "library-RTL.css",
			"size": 30739,
			"theme": "sap_fiori_3"
		},
		{
			"name": "library-parameters.json",
			"size": 3110,
			"theme": "sap_fiori_3"
		},
		{
			"name": "library.css",
			"size": 30732,
			"theme": "sap_fiori_3"
		},
		{
			"name": "library.less",
			"size": 9586,
			"designtime": true,
			"theme": "sap_fiori_3"
		},
		{
			"name": "library.source.less",
			"size": 573,
			"designtime": true,
			"theme": "sap_fiori_3"
		},
		{
			"name": "library_skeleton-RTL.css",
			"size": 31523,
			"theme": "sap_fiori_3"
		},
		{
			"name": "library_skeleton.css",
			"size": 31516,
			"theme": "sap_fiori_3"
		}
	]
}